vai/__init__.py
vai/main.py
vai/package_defaults/config.yaml
vai/package_defaults/static/favicon.png
vai/package_defaults/static/logo.png
vai/package_defaults/static/script.js
vai/package_defaults/static/style.css
vai/package_defaults/templates/layout_no_header.html
vai_ssg-1.1.2.dist-info/licenses/LICENSE
vai_ssg-1.1.2.dist-info/METADATA
vai_ssg-1.1.2.dist-info/WHEEL
vai_ssg-1.1.2.dist-info/entry_points.txt
vai_ssg-1.1.2.dist-info/top_level.txt
vai_ssg-1.1.2.dist-info/RECORD
