Metadata-Version: 2.4
Name: vai-ssg
Version: 1.1.2
Summary: An Opinonated But Customisable Static Site Generator Made In Python
Author-email: Naresh <nareshix66@gmail.com>
Maintainer-email: Naresh <nareshix66@gmail.com>
License-Expression: MIT
Keywords: vai,python,python3,fast,static site generator,ssg
Classifier: Intended Audience :: Developers
Classifier: Programming Language :: Python :: 3
Classifier: Programming Language :: Python :: 3.9
Classifier: Programming Language :: Python :: 3.10
Classifier: Programming Language :: Python :: 3.11
Classifier: Programming Language :: Python :: 3.12
Classifier: Topic :: Internet :: WWW/HTTP :: Site Management
Classifier: Topic :: Text Processing :: Markup :: Markdown
Classifier: Topic :: Documentation
Requires-Python: >=3.9
License-File: LICENSE
Requires-Dist: beautifulsoup4==4.13.4
Requires-Dist: Jinja2==3.1.6
Requires-Dist: livereload==2.7.1
Requires-Dist: Markdown==3.8
Requires-Dist: MarkupSafe==3.0.2
Requires-Dist: minify_html==0.16.4
Requires-Dist: Pygments==2.19.1
Requires-Dist: PyYAML==6.0.2
Requires-Dist: rcssmin==1.2.1
Requires-Dist: rjsmin==1.2.4
Dynamic: license-file
